LICENSE.md
README.md
setup.py
test/test_receiver.py
test/test_scenario.py
test/test_vled.py
vlcSim.egg-info/PKG-INFO
vlcSim.egg-info/SOURCES.txt
vlcSim.egg-info/dependency_links.txt
vlcSim.egg-info/not-zip-safe
vlcSim.egg-info/requires.txt
vlcSim.egg-info/top_level.txt
vlcsim/__init__.py
vlcsim/controller.py
vlcsim/scene.py
vlcsim/simulator.py